Workbook

Sheet Student Sheet
A1: Students Attendance Sheet (Jan) Class 6
A3: Roll# | B3: Name | C3: 1 | D3: 2 | E3: 3 | F3: 4 | G3: 5 | H3: 6 | I3: 7 | J3: 8 | K3: 9 | L3: 10 | M3: 11 | N3: 12 | O3: 13 | P3: 14 | Q3: 15 | R3: 16 | S3: 17 | T3: 18 | U3: 19 | V3: 20 | W3: 21 | X3: 22 | Y3: 23 | Z3: 24 | AA3: 25 | AB3: 26 | AC3: 27 | AD3: 28 | AE3: 29 | AF3: 30 | AG3: 31 | AH3: Present | AI3: Absent | AJ3: Leave
A4: 1 | B4: Ali | D4: P | E4: P | F4: P | G4: P | H4: P | I4: A | K4: P | L4: P | M4: P | N4: P | O4: P | P4: P | R4: P | S4: P | T4: P | U4: P | V4: P | W4: P | Y4: P | Z4: P | AA4: P | AB4: P | AC4: P | AD4: P | AF4: P | AG4: P | AH4: =COUNTIF(C4:AG4,"P") -> 25 | AI4: =COUNTIF(E4:AH4,"A") -> 1 | AJ4: =COUNTIF(F4:AI4,"L") -> 0
A5: 2 | B5: Amir | D5: P | E5: P | F5: A | G5: P | H5: P | I5: P | K5: P | L5: P | M5: P | N5: P | O5: P | P5: P | R5: P | S5: P | T5: P | U5: P | V5: P | W5: L | Y5: L | Z5: P | AA5: A | AB5: P | AC5: P | AD5: P | AF5: P | AG5: P | AH5: =COUNTIF(C5:AG5,"P") -> 22 | AI5: =COUNTIF(E5:AH5,"A") -> 2 | AJ5: =COUNTIF(F5:AI5,"L") -> 2
A6: 3 | B6: Kamran | D6: P | E6: P | F6: P | G6: P | H6: L | I6: P | K6: P | L6: P | M6: P | N6: P | O6: P | P6: A | R6: P | S6: A | T6: P | U6: A | V6: P | W6: P | Y6: P | Z6: P | AA6: P | AB6: P | AC6: P | AD6: P | AF6: P | AG6: P | AH6: =COUNTIF(C6:AG6,"P") -> 22 | AI6: =COUNTIF(E6:AH6,"A") -> 3 | AJ6: =COUNTIF(F6:AI6,"L") -> 1
A7: 4 | B7: Bilal | D7: P | E7: P | F7: P | G7: A | H7: P | I7: P | K7: A | L7: P | M7: L | N7: P | O7: P | P7: P | R7: P | S7: P | T7: P | U7: P | V7: A | W7: P | Y7: L | Z7: P | AA7: P | AB7: P | AC7: P | AD7: L | AF7: P | AG7: P | AH7: =COUNTIF(C7:AG7,"P") -> 20 | AI7: =COUNTIF(E7:AH7,"A") -> 3 | AJ7: =COUNTIF(F7:AI7,"L") -> 3
A8: 5 | B8: Zaid | D8: P | E8: P | F8: P | G8: P | H8: P | I8: P | K8: P | L8: P | M8: P | N8: P | O8: P | P8: P | R8: P | S8: P | T8: P | U8: P | V8: P | W8: P | Y8: P | Z8: P | AA8: P | AB8: P | AC8: P | AD8: P | AF8: P | AG8: P | AH8: =COUNTIF(C8:AG8,"P") -> 26 | AI8: =COUNTIF(E8:AH8,"A") -> 0 | AJ8: =COUNTIF(F8:AI8,"L") -> 0
A9: 6 | B9: Amna | D9: P | E9: P | F9: P | G9: A | H9: P | I9: A | K9: P | L9: A | M9: P | N9: A | O9: P | P9: P | R9: P | S9: L | T9: P | U9: P | V9: P | W9: P | Y9: P | Z9: P | AA9: P | AB9: A | AC9: P | AD9: P | AF9: P | AG9: P | AH9: =COUNTIF(C9:AG9,"P") -> 20 | AI9: =COUNTIF(E9:AH9,"A") -> 5 | AJ9: =COUNTIF(F9:AI9,"L") -> 1
A10: 7 | B10: Basit | D10: P | E10: P | F10: P | G10: P | H10: P | I10: P | K10: P | L10: P | M10: P | N10: P | O10: P | P10: P | R10: P | S10: P | T10: P | U10: P | V10: P | W10: P | Y10: P | Z10: P | AA10: P | AB10: P | AC10: P | AD10: P | AF10: P | AG10: P | AH10: =COUNTIF(C10:AG10,"P") -> 26 | AI10: =COUNTIF(E10:AH10,"A") -> 0 | AJ10: =COUNTIF(F10:AI10,"L") -> 0
A11: 8 | B11: Akram | D11: P | E11: P | F11: P | G11: P | H11: A | I11: P | K11: P | L11: L | M11: P | N11: P | O11: A | P11: P | R11: P | S11: A | T11: P | U11: A | V11: P | W11: P | Y11: P | Z11: P | AA11: L | AB11: P | AC11: P | AD11: P | AF11: P | AG11: P | AH11: =COUNTIF(C11:AG11,"P") -> 20 | AI11: =COUNTIF(E11:AH11,"A") -> 4 | AJ11: =COUNTIF(F11:AI11,"L") -> 2
A12: 9 | B12: Zahid | D12: P | E12: P | F12: P | G12: P | H12: P | I12: P | K12: A | L12: P | M12: P | N12: P | O12: P | P12: P | R12: P | S12: P | T12: P | U12: P | V12: P | W12: P | Y12: P | Z12: P | AA12: P | AB12: P | AC12: L | AD12: P | AF12: P | AG12: A | AH12: =COUNTIF(C12:AG12,"P") -> 23 | AI12: =COUNTIF(E12:AH12,"A") -> 2 | AJ12: =COUNTIF(F12:AI12,"L") -> 1
A13: 10 | B13: Arbaz | D13: P | E13: P | F13: P | G13: P | H13: P | I13: P | K13: P | L13: P | M13: P | N13: P | O13: P | P13: P | R13: P | S13: P | T13: P | U13: P | V13: P | W13: P | Y13: P | Z13: P | AA13: P | AB13: P | AC13: P | AD13: P | AF13: P | AG13: P | AH13: =COUNTIF(C13:AG13,"P") -> 26 | AI13: =COUNTIF(E13:AH13,"A") -> 0 | AJ13: =COUNTIF(F13:AI13,"L") -> 0
A15: Total Present | C15: =COUNTIF(C4:C13,"P") -> 0 | D15: =COUNTIF(D4:D13,"P") -> 10 | E15: =COUNTIF(E4:E13,"P") -> 10 | F15: =COUNTIF(F4:F13,"P") -> 9 | G15: =COUNTIF(G4:G13,"P") -> 8 | H15: =COUNTIF(H4:H13,"P") -> 8 | I15: =COUNTIF(I4:I13,"P") -> 8 | J15: =COUNTIF(J4:J13,"P") -> 0 | ... AG15: =COUNTIF(AG4:AG13,"P") -> 9
A16: Total Absent | C16: =COUNTIF(C5:C14,"A") -> 0 | D16: =COUNTIF(D5:D14,"A") -> 0 | E16: =COUNTIF(E5:E14,"A") -> 0 | F16: =COUNTIF(F5:F14,"A") -> 1 | G16: =COUNTIF(G5:G14,"A") -> 2 | H16: =COUNTIF(H5:H14,"A") -> 1 | I16: =COUNTIF(I5:I14,"A") -> 1 | J16: =COUNTIF(J5:J14,"A") -> 0 | ... AG16: =COUNTIF(AG5:AG14,"A") -> 1
A17: Total Leave | C17: =COUNTIF(C6:C15,"l") -> 0 | D17: =COUNTIF(D6:D15,"l") -> 0 | E17: =COUNTIF(E6:E15,"l") -> 0 | F17: =COUNTIF(F6:F15,"l") -> 0 | G17: =COUNTIF(G6:G15,"l") -> 0 | H17: =COUNTIF(H6:H15,"l") -> 1 | I17: =COUNTIF(I6:I15,"l") -> 0 | J17: =COUNTIF(J6:J15,"l") -> 0 | ... AG17: =COUNTIF(AG6:AG15,"l") -> 0

Sheet Payroll
A2: Employee Payroll Sheet
A5: Sr No | B5: Emp Name | C5: Designation | D5: Basic Pay | E5: Attendance | F5: Salary | G5: Allowances | J5: Gross pay | K5: Deductions | N5: Net salary | O5: Grade
G7: House Rent | H7: Conveyance | I7: Medical | K7: GP Fund | L7: Tax | M7: Total Deduction
A8: 1 | B8: Ali | C8: Manager | D8: 30000 | E8: ='Student Sheet'!AH4 -> 25 | F8: =D8/30*E8 -> 25000 | G8: =F8*20% -> 5000 | H8: =F8*10% -> 2500 | I8: =F8*5% -> 1250 | J8: =F8+G8+H8+I8 -> 33750 | K8: =J8*12% -> 4050 | L8: =J8*10% -> 3375 | M8: =K8+L8 -> 7425 | N8: =J8-M8 -> 26325 | O8: =IF(N8>=30000,"A",IF(N8>=20000,"B","C")) -> B
A9: 2 | B9: Amir | C9: HR | D9: 40000 | E9: ='Student Sheet'!AH5 -> 22 | F9: =D9/30*E9 -> 29333.333 | G9: =F9*20% -> 5866.6667 | H9: =F9*10% -> 2933.3333 | I9: =F9*5% -> 1466.6667 | J9: =F9+G9+H9+I9 -> 39600 | K9: =J9*12% -> 4752 | L9: =J9*10% -> 3960 | M9: =K9+L9 -> 8712 | N9: =J9-M9 -> 30888 | O9: =IF(N9>=30000,"A",IF(N9>=20000,"B","C")) -> A
A10: 3 | B10: Kamran | C10: Accountant | D10: 45000 | E10: ='Student Sheet'!AH6 -> 22 | F10: =D10/30*E10 -> 33000 | G10: =F10*20% -> 6600 | H10: =F10*10% -> 3300 | I10: =F10*5% -> 1650 | J10: =F10+G10+H10+I10 -> 44550 | K10: =J10*12% -> 5346 | L10: =J10*10% -> 4455 | M10: =K10+L10 -> 9801 | N10: =J10-M10 -> 34749 | O10: =IF(N10>=30000,"A",IF(N10>=20000,"B","C")) -> A
A11: 4 | B11: Bilal | C11: PA | D11: 25000 | E11: ='Student Sheet'!AH7 -> 20 | F11: =D11/30*E11 -> 16666.667 | G11: =F11*20% -> 3333.3333 | H11: =F11*10% -> 1666.6667 | I11: =F11*5% -> 833.33333 | J11: =F11+G11+H11+I11 -> 22500 | K11: =J11*12% -> 2700 | L11: =J11*10% -> 2250 | M11: =K11+L11 -> 4950 | N11: =J11-M11 -> 17550 | O11: =IF(N11>=30000,"A",IF(N11>=20000,"B","C")) -> C
A12: 5 | B12: Zaid | C12: Helper | D12: 15000 | E12: ='Student Sheet'!AH8 -> 26 | F12: =D12/30*E12 -> 13000 | G12: =F12*20% -> 2600 | H12: =F12*10% -> 1300 | I12: =F12*5% -> 650 | J12: =F12+G12+H12+I12 -> 17550 | K12: =J12*12% -> 2106 | L12: =J12*10% -> 1755 | M12: =K12+L12 -> 3861 | N12: =J12-M12 -> 13689 | O12: =IF(N12>=30000,"A",IF(N12>=20000,"B","C")) -> C
